multiaddr/__init__.py
multiaddr/exceptions.py
multiaddr/multiaddr.py
multiaddr/protocols.py
multiaddr/transforms.py
multiaddr/utils.py
multiaddr/codecs/__init__.py
multiaddr/codecs/cid.py
multiaddr/codecs/domain.py
multiaddr/codecs/fspath.py
multiaddr/codecs/garlic32.py
multiaddr/codecs/garlic64.py
multiaddr/codecs/http_path.py
multiaddr/codecs/ip4.py
multiaddr/codecs/ip6.py
multiaddr/codecs/ipcidr.py
multiaddr/codecs/memory.py
multiaddr/codecs/onion.py
multiaddr/codecs/onion3.py
multiaddr/codecs/uint16be.py
multiaddr/codecs/utf8.py
multiaddr/resolvers/__init__.py
multiaddr/resolvers/base.py
multiaddr/resolvers/dns.py
multiaddr-0.0.12.dist-info/licenses/AUTHORS
multiaddr-0.0.12.dist-info/licenses/LICENSE-APACHE2
multiaddr-0.0.12.dist-info/licenses/LICENSE-MIT
multiaddr-0.0.12.dist-info/METADATA
multiaddr-0.0.12.dist-info/WHEEL
multiaddr-0.0.12.dist-info/top_level.txt
multiaddr-0.0.12.dist-info/RECORD
