Metadata-Version: 2.4
Name: multiaddr
Version: 0.0.12
Summary: Python implementation of jbenet's multiaddr
Author-email: Steven Buss <steven.buss@gmail.com>
Maintainer: acul71
Maintainer-email: pacrob <pacrob@protonmail.com>, Manu Sheel Gupta <manu@seeta.in>
License: MIT License
Project-URL: Homepage, https://github.com/multiformats/py-multiaddr
Project-URL: Download, https://github.com/multiformats/py-multiaddr/tarball/0.0.12
Keywords: multiaddr
Classifier: Development Status :: 2 - Pre-Alpha
Classifier: Intended Audience :: Developers
Classifier: License :: OSI Approved :: MIT License
Classifier: Natural Language :: English
Classifier: Programming Language :: Python :: 3
Classifier: Programming Language :: Python :: 3.10
Classifier: Programming Language :: Python :: 3.11
Classifier: Programming Language :: Python :: 3.12
Classifier: Programming Language :: Python :: 3.13
Requires-Python: <4.0,>=3.10
License-File: LICENSE-APACHE2
License-File: LICENSE-MIT
License-File: AUTHORS
Requires-Dist: base58
Requires-Dist: dnspython>=2.7.0
Requires-Dist: idna
Requires-Dist: netaddr
Requires-Dist: psutil
Requires-Dist: py-cid>=0.3.1
Requires-Dist: py-multicodec>=0.2.0
Requires-Dist: trio-typing>=0.0.4
Requires-Dist: trio>=0.26.0
Requires-Dist: varint
Provides-Extra: dev
Requires-Dist: Sphinx>=5.0.0; extra == "dev"
Requires-Dist: build>=0.9.0; extra == "dev"
Requires-Dist: bump_my_version>=1.2.0; extra == "dev"
Requires-Dist: coverage>=6.5.0; extra == "dev"
Requires-Dist: mypy; extra == "dev"
Requires-Dist: pre-commit; extra == "dev"
Requires-Dist: pyrefly; extra == "dev"
Requires-Dist: pyright; extra == "dev"
Requires-Dist: pytest; extra == "dev"
Requires-Dist: pytest-cov; extra == "dev"
Requires-Dist: pytest-runner; extra == "dev"
Requires-Dist: pytest-trio>=0.5.2; extra == "dev"
Requires-Dist: ruff; extra == "dev"
Requires-Dist: towncrier<25,>=24; extra == "dev"
Requires-Dist: tox>=4.10.0; extra == "dev"
Requires-Dist: twine; extra == "dev"
Requires-Dist: types-netaddr; extra == "dev"
Requires-Dist: types-psutil; extra == "dev"
Requires-Dist: watchdog>=3.0.0; extra == "dev"
Requires-Dist: wheel>=0.31.0; extra == "dev"
Dynamic: license-file
